{
  "Множество ИБ" : 
  {
    "История болезни или наблюдений v.4" :
    {

      "ИБ 23-1-адн" : 
      {
        "дата обращения" :

          "21.12.2020-00:00:00.000"
        ,
        "Паспортная часть" :


          {
            "Факт" :
            {

              "Возраст" : 
              {
                "Числовые значения" :


                  {
                    "значение" :

                      54.0
                    ,
                    "единица измерения" :

                      "год"                  }
              }
,
              "Пол" : 
              {
                "Качественные значения" :


                  {
                    "значение" :
                    [

                      "женский"                    ]
                  }
              }
            }
          }

        ,
        "Результаты компьютерной постановки диагноза" :


          {
          }

        ,
        "Жалобы" :


          {
            "Признак" :
            [

            {
              "Боль в горле" : 
              {
                "Характеристика" :
                {

                  "Присутствие" : 
                  {
                    "Качественные значения" :


                      {
                        "значение" :
                        [

                          "имеется"                        ]
                      }
                  }
                }
              }

            },
            {
              "Заложенность носа" : 
              {
                "Характеристика" :
                {

                  "Наличие жалобы" : 
                  {
                    "Качественные значения" :


                      {
                        "значение" :
                        [

                          "имеется"                        ]
                      }
                  }
                }
              }

            },
            {
              "Общая слабость" : 
              {
                "Характеристика" :
                {

                  "Наличие жалобы" : 
                  {
                    "Качественные значения" :


                      {
                        "значение" :
                        [

                          "имеется"                        ]
                      }
                  }
,
                  "Выраженность" : 
                  {
                    "Качественные значения" :


                      {
                        "значение" :
                        [

                          "умеренно выраженная"                        ]
                      }
                  }
                }
              }

            },
            {
              "Першение в горле" : 
              {
                "Качественные значения" :


                  {
                    "значение" :
                    [

                      "имеется"                    ]
                  }
              }

            },
            {
              "Блефароспазм" : 
              {
                "Характеристика" :
                {

                  "Наличие жалобы" : 
                  {
                    "Качественные значения" :


                      {
                        "значение" :
                        [

                          "имеется"                        ]
                      }
                  }
                }
              }

            },
            {
              "Выделение из полости носа" : 
              {
                "Характеристика" :
                {

                  "Наличие жалобы" : 
                  {
                    "Качественные значения" :


                      {
                        "значение" :
                        [

                          "имеется"                        ]
                      }
                  }
,
                  "Характер отделяемого" : 
                  {
                    "Качественные значения" :


                      {
                        "значение" :
                        [

                          "серозное"                        ]
                      }
                  }
,
                  "Количество отделяемого" : 
                  {
                    "Качественные значения" :


                      {
                        "значение" :
                        [

                          "обильное"                        ]
                      }
                  }
                }
              }

            },
            {
              "Слезотечение" : 
              {
                "Характеристика" :
                {

                  "Присутствие" : 
                  {
                    "Качественные значения" :


                      {
                        "значение" :
                        [

                          "имеется"                        ]
                      }
                  }
                }
              }

            }            ]
          }

        ,
        "Объективное состояние" :


          {
            "Осмотр по системам" :


              {
                "Система органов дыхания" :


                  {
                    "Признак" :
                    [

                    {
                      "Дыхание везикулярное" : 
                      {
                        "Характеристика" :
                        {

                          "Присутствие" : 
                          {
                            "Качественные значения" :


                              {
                                "значение" :
                                [

                                  "выслушивается"                                ]
                              }
                          }
,
                          "Изменение везикулярного дыхания" : 
                          {
                            "Качественные значения" :


                              {
                                "значение" :
                                [

                                  "не изменено"                                ]
                              }
                          }
                        }
                      }

                    },
                    {
                      "Частота дыхания" : 
                      {
                        "Числовые значения" :


                          {
                            "значение" :

                              18.0
                            ,
                            "единица измерения" :

                              "частота дыхательных движений в минуту"                          }
                      }

                    }                    ]
                  }

                ,
                "Система кровообращения" :


                  {
                    "Признак" :
                    [

                    {
                      "Систолическое артериальное давление" : 
                      {
                        "Числовые значения" :


                          {
                            "значение" :

                              120.0
                            ,
                            "единица измерения" :

                              "мм.рт.ст."                          }
                      }

                    },
                    {
                      "Диастолическое артериальное давление" : 
                      {
                        "Числовые значения" :


                          {
                            "значение" :

                              60.0
                            ,
                            "единица измерения" :

                              "мм.рт.ст."                          }
                      }

                    },
                    {
                      "Звучность тонов сердца" : 
                      {
                        "Качественные значения" :


                          {
                            "значение" :
                            [

                              "ясные"                            ]
                          }
                      }

                    },
                    {
                      "Ритмичность тонов сердца" : 
                      {
                        "Качественные значения" :


                          {
                            "значение" :
                            [

                              "ритмичные"                            ]
                          }
                      }

                    },
                    {
                      "Частота пульса на лучевой артерии" : 
                      {
                        "Числовые значения" :


                          {
                            "значение" :

                              106.0
                            ,
                            "единица измерения" :

                              "уд/мин"                          }
                      }

                    },
                    {
                      "Частота сердечных сокращений" : 
                      {
                        "Числовые значения" :


                          {
                            "значение" :

                              100.0
                            ,
                            "единица измерения" :

                              "уд/мин"                          }
                      }

                    }                    ]
                  }

                ,
                "Система органов мочевыделения" :


                  {
                    "Признак" :
                    [

                    {
                      "Симптом Пастернацкого" : 
                      {
                        "Качественные значения" :


                          {
                            "значение" :
                            [

                              "отрицательный с обеих сторон"                            ]
                          }
                      }

                    }                    ]
                  }
              }

            ,
            "Общий осмотр" :


              {
                "Признак" :
                [

                {
                  "Общее состояние" : 
                  {
                    "Качественные значения" :


                      {
                        "значение" :
                        [

                          "удовлетворительное"                        ]
                      }
                  }

                },
                {
                  "Влажность кожи" : 
                  {
                    "Качественные значения" :


                      {
                        "значение" :
                        [

                          "нормальная"                        ]
                      }
                  }

                },
                {
                  "Обложенность языка" : 
                  {
                    "Характеристика" :
                    {

                      "Присутствие" : 
                      {
                        "Качественные значения" :


                          {
                            "значение" :
                            [

                              "отсутствует"                            ]
                          }
                      }
                    }
                  }

                },
                {
                  "Окраска кожи" : 
                  {
                    "Качественные значения" :


                      {
                        "значение" :
                        [

                          "бледно-розовая"                        ]
                      }
                  }

                },
                {
                  "Температура тела" : 
                  {
                    "Характеристика" :
                    {

                      "Повышение" : 
                      {
                        "Качественные значения" :


                          {
                            "значение" :
                            [

                              "имеется"                            ]
                          }
                      }
,
                      "Значение" : 
                      {
                        "Числовые значения" :


                          {
                            "значение" :

                              38.0
                            ,
                            "единица измерения" :

                              "°С"                          }
                      }
                    }
                  }

                },
                {
                  "Окраска передней стенки глотки" : 
                  {
                    "Качественные значения" :


                      {
                        "значение" :
                        [

                          "гиперемия"                        ]
                      }
                  }

                },
                {
                  "Окраска слизистой полости носа" : 
                  {
                    "Качественные значения" :


                      {
                        "значение" :
                        [

                          "гиперемия"                        ]
                      }
                  }

                },
                {
                  "Подчелюстные лимфатические узлы" : 
                  {
                    "Характеристика" :
                    {

                      "Увеличение" : 
                      {
                        "Качественные значения" :


                          {
                            "значение" :
                            [

                              "имеется"                            ]
                          }
                      }
,
                      "Болезненность при пальпации" : 
                      {
                        "Качественные значения" :


                          {
                            "значение" :
                            [

                              "имеется"                            ]
                          }
                      }
                    }
                  }

                },
                {
                  "Сознание" : 
                  {
                    "Качественные значения" :


                      {
                        "значение" :
                        [

                          "ясное"                        ]
                      }
                  }

                },
                {
                  "Небные миндалины" : 
                  {
                    "Характеристика" :
                    {

                      "Присутствие" : 
                      {
                        "Качественные значения" :


                          {
                            "значение" :
                            [

                              "имеются"                            ]
                          }
                      }
,
                      "Цвет" : 
                      {
                        "Качественные значения" :


                          {
                            "значение" :
                            [

                              "гиперемия"                            ]
                          }
                      }
,
                      "Увеличение" : 
                      {
                        "Качественные значения" :


                          {
                            "значение" :
                            [

                              "гипертрофия"                            ]
                          }
                      }
,
                      "Отечность" : 
                      {
                        "Качественные значения" :


                          {
                            "значение" :
                            [

                              "имеется"                            ]
                          }
                      }
                    }
                  }

                }                ]
              }
          }

        ,
        "Результаты компьютерного назначения лечения" :


          {
          }
      }
    }
  }

}
